plot2svg/__init__.py
plot2svg/core.py
plot2svg-0.0.4.dist-info/LICENSE
plot2svg-0.0.4.dist-info/METADATA
plot2svg-0.0.4.dist-info/WHEEL
plot2svg-0.0.4.dist-info/top_level.txt
plot2svg-0.0.4.dist-info/RECORD
