Metadata-Version: 2.1
Name: plot2svg
Version: 0.0.4
Summary: A simple plot tool to generate small SVG files
Home-page: https://github.com/guofei9987/plot2svg
Author: Guo Fei
Author-email: guofei9987@foxmail.com
License: MIT
Platform: linux
Platform: windows
Platform: macos
Requires-Python: >=3.5
